ltk/__init__.py
ltk/api_uri.py
ltk/apicalls.py
ltk/auth.py
ltk/check_connection.py
ltk/commands.py
ltk/constants.py
ltk/exceptions.py
ltk/git_auto.py
ltk/locales.py
ltk/logger.py
ltk/managers.py
ltk/utils.py
ltk/watch.py
ltk/watchhandler.py
ltk/__pycache__/__init__.cpython-39.pyc
ltk/__pycache__/api_uri.cpython-39.pyc
ltk/__pycache__/apicalls.cpython-39.pyc
ltk/__pycache__/check_connection.cpython-39.pyc
ltk/__pycache__/commands.cpython-39.pyc
ltk/__pycache__/constants.cpython-39.pyc
ltk/__pycache__/exceptions.cpython-39.pyc
ltk/__pycache__/git_auto.cpython-39.pyc
ltk/__pycache__/locales.cpython-39.pyc
ltk/__pycache__/logger.cpython-39.pyc
ltk/__pycache__/managers.cpython-39.pyc
ltk/__pycache__/utils.cpython-39.pyc
ltk/__pycache__/watch.cpython-39.pyc
ltk/__pycache__/watchhandler.cpython-39.pyc
ltk/actions/__init__.py
ltk/actions/action.py
ltk/actions/add_action.py
ltk/actions/clean_action.py
ltk/actions/clone_action.py
ltk/actions/config_action.py
ltk/actions/download_action.py
ltk/actions/filters_action.py
ltk/actions/import_action.py
ltk/actions/init_action.py
ltk/actions/list_action.py
ltk/actions/move_action.py
ltk/actions/pull_action.py
ltk/actions/push_action.py
ltk/actions/reference_action.py
ltk/actions/request_action.py
ltk/actions/rm_action.py
ltk/actions/status_action.py
ltk/actions/__pycache__/__init__.cpython-39.pyc
ltk/actions/__pycache__/action.cpython-39.pyc
ltk/actions/__pycache__/add_action.cpython-39.pyc
ltk/actions/__pycache__/clean_action.cpython-39.pyc
ltk/actions/__pycache__/clone_action.cpython-39.pyc
ltk/actions/__pycache__/config_action.cpython-39.pyc
ltk/actions/__pycache__/download_action.cpython-39.pyc
ltk/actions/__pycache__/filters_action.cpython-39.pyc
ltk/actions/__pycache__/import_action.cpython-39.pyc
ltk/actions/__pycache__/init_action.cpython-39.pyc
ltk/actions/__pycache__/list_action.cpython-39.pyc
ltk/actions/__pycache__/move_action.cpython-39.pyc
ltk/actions/__pycache__/pull_action.cpython-39.pyc
ltk-1.3.14.dist-info/LICENSE.md
ltk-1.3.14.dist-info/METADATA
ltk-1.3.14.dist-info/WHEEL
ltk-1.3.14.dist-info/entry_points.txt
ltk-1.3.14.dist-info/top_level.txt
ltk-1.3.14.dist-info/RECORD
