Metadata-Version: 2.1
Name: ltk
Version: 1.3.14
Summary: The Lingotek Filesystem Connector (ltk) links your files and folders to the Translation Network™
Home-page: https://github.com/Lingotek/filesystem-connector
Author: Lingotek
Author-email: integrations@lingotek.com
License: MIT
License-File: LICENSE.md
Requires-Dist: click
Requires-Dist: requests[security]
Requires-Dist: tinydb
Requires-Dist: watchdog
Requires-Dist: gitpython
Requires-Dist: pexpect
Requires-Dist: blessings
Requires-Dist: tabulate
Provides-Extra: security
Requires-Dist: pyOpenSSL ; extra == 'security'
Requires-Dist: ndg-httpsclient ; extra == 'security'
Requires-Dist: pyasn1 ; extra == 'security'
